datmo/VERSION
datmo/__init__.py
datmo/__main__.py
datmo/config.py
datmo/deploy.py
datmo/logger.py
datmo/monitoring.py
datmo/snapshot.py
datmo/cli/__init__.py
datmo/cli/main.py
datmo/cli/parser.py
datmo/cli/command/__init__.py
datmo/cli/command/base.py
datmo/cli/command/datmo_command.py
datmo/cli/command/deploy.py
datmo/cli/command/environment.py
datmo/cli/command/project.py
datmo/cli/command/run.py
datmo/cli/command/snapshot.py
datmo/cli/command/workspace.py
datmo/cli/driver/__init__.py
datmo/cli/driver/helper.py
datmo/cli/driver/parser.py
datmo/core/__init__.py
datmo/core/controller/__init__.py
datmo/core/controller/base.py
datmo/core/controller/model.py
datmo/core/controller/project.py
datmo/core/controller/snapshot.py
datmo/core/controller/task.py
datmo/core/controller/code/__init__.py
datmo/core/controller/code/code.py
datmo/core/controller/code/driver/__init__.py
datmo/core/controller/code/driver/file.py
datmo/core/controller/code/driver/git.py
datmo/core/controller/deploy/__init__.py
datmo/core/controller/deploy/deploy.py
datmo/core/controller/deploy/driver/__init__.py
datmo/core/controller/deploy/driver/datmo_microservice.py
datmo/core/controller/environment/__init__.py
datmo/core/controller/environment/environment.py
datmo/core/controller/environment/driver/__init__.py
datmo/core/controller/environment/driver/dockerenv.py
datmo/core/controller/environment/driver/config/__init__.py
datmo/core/controller/environment/driver/config/docker.json
datmo/core/controller/environment/driver/templates/__init__.py
datmo/core/controller/environment/driver/templates/baseDockerfile
datmo/core/controller/environment/driver/templates/python2Dockerfile
datmo/core/controller/environment/driver/templates/python3Dockerfile
datmo/core/controller/file/__init__.py
datmo/core/controller/file/file_collection.py
datmo/core/controller/file/driver/__init__.py
datmo/core/controller/file/driver/local.py
datmo-0.0.40.dist-info/DESCRIPTION.rst
datmo-0.0.40.dist-info/LICENSE.txt
datmo-0.0.40.dist-info/METADATA
datmo-0.0.40.dist-info/RECORD
datmo-0.0.40.dist-info/WHEEL
datmo-0.0.40.dist-info/entry_points.txt
datmo-0.0.40.dist-info/metadata.json
datmo-0.0.40.dist-info/top_level.txt
