Metadata-Version: 2.0
Name: datmo
Version: 0.0.40
Summary: Open source model tracking tool for developers
Home-page: https://github.com/datmo/datmo
Author: datmo developers
Author-email: developer@datmo.com
License: See LICENSE.txt
Keywords: setup,distutils
Platform: UNKNOWN
Classifier: Development Status :: 2 - Pre-Alpha
Classifier: Environment :: Console
Classifier: Intended Audience :: Developers
Classifier: Intended Audience :: Information Technology
Classifier: License :: OSI Approved :: Apache Software License
Classifier: Operating System :: OS Independent
Classifier: Programming Language :: Python :: 2
Classifier: Programming Language :: Python :: 2.7
Classifier: Programming Language :: Python :: 3
Classifier: Programming Language :: Python :: 3.4
Classifier: Programming Language :: Python :: 3.5
Classifier: Programming Language :: Python :: 3.6
Requires-Dist: future (>=0.16.0)
Requires-Dist: enum34 (>=1.1.6)
Requires-Dist: glob2 (>=0.5)
Requires-Dist: docker (==3.6.0)
Requires-Dist: pyyaml (>=3.12)
Requires-Dist: pytz (>=2017.3)
Requires-Dist: tzlocal (>=1.5.1)
Requires-Dist: rsfile (>=2.1)
Requires-Dist: humanfriendly (>=3.6.1)
Requires-Dist: python-slugify (>=1.2.4)
Requires-Dist: giturlparse.py (>=0.0.5)
Requires-Dist: blitzdb (>=0.2.12)
Requires-Dist: kids.cache (>=0.0.7)
Requires-Dist: pymongo (>=3.6.0)
Requires-Dist: checksumdir (>=1.1.4)
Requires-Dist: semver (>=2.7.8)
Requires-Dist: backports.ssl-match-hostname (>=3.5.0.1)
Requires-Dist: timeout-decorator (>=0.4.0)
Requires-Dist: cerberus (>=1.2)
Requires-Dist: pytest (==3.0.4)
Requires-Dist: pathspec (>=0.5.6)
Requires-Dist: psutil (>=4.4.2)
Requires-Dist: flask (>=0.10.1)
Requires-Dist: jinja2 (>=2.7.3)
Requires-Dist: markupsafe (>=0.23)
Requires-Dist: werkzeug (>=0.9.6)
Requires-Dist: beautifulsoup4 (>=4.3.2)
Requires-Dist: gunicorn (>=19.1.1)
Requires-Dist: itsdangerous (>=0.24)
Requires-Dist: six (>=1.8.0)
Requires-Dist: urllib3 (==1.23)
Requires-Dist: chardet (==3.0.2)
Requires-Dist: prettytable (>=0.7.2)
Requires-Dist: requests (>=2.20.0)
Requires-Dist: plotly (==3.3.0)
Requires-Dist: jsonschema (==2.6.0)
Requires-Dist: celery (==4.2.1)
